pbwrap/__init__.py
pbwrap/asyncpbwrap.py
pbwrap/constants.py
pbwrap/formatter.py
pbwrap/models.py
pbwrap/pbwrap.py
pbwrap-1.5.0.dist-info/LICENSE
pbwrap-1.5.0.dist-info/METADATA
pbwrap-1.5.0.dist-info/WHEEL
pbwrap-1.5.0.dist-info/RECORD
