Metadata-Version: 2.3
Name: pbwrap
Version: 1.5.0
Summary: A Pastebin API Wrapper for Python
License: MIT
Keywords: pastebin,pbwrap,wrapper,api
Author: Mikts
Author-email: mikts94@gmail.com
Requires-Python: >=3.9.0,<4.0
Classifier: Development Status :: 5 - Production/Stable
Classifier: Intended Audience :: Developers
Classifier: License :: OSI Approved :: MIT License
Classifier: Operating System :: OS Independent
Classifier: Programming Language :: Python :: 3
Classifier: Programming Language :: Python :: 3.9
Classifier: Programming Language :: Python :: 3.10
Classifier: Programming Language :: Python :: 3.11
Classifier: Programming Language :: Python :: 3.12
Classifier: Programming Language :: Python :: 3.13
Classifier: Topic :: Software Development
Classifier: Topic :: Utilities
Requires-Dist: aiohttp (>=3.6,<4.0)
Requires-Dist: requests (>=2.23,<3.0)
Requires-Dist: twine (>=3.1,<4.0)
Requires-Dist: wheel (>=0.38.1,<0.39.0)
Project-URL: Documentation, https://pbwrap.readthedocs.io/en/latest/
Project-URL: Homepage, https://github.com/Mikts/pbwrap
Project-URL: Repository, https://github.com/Mikts/pbwrap
